filesystemlib/__init__.py
filesystemlib/chmod.py
filesystemlib/errors.py
filesystemlib/internal.py
filesystemlib/makedirs.py
filesystemlib/move.py
filesystemlib/walk.py
filesystemlib/extended/__init__.py
filesystemlib/extended/macos.py
filesystemlib-0.1.0.dist-info/METADATA
filesystemlib-0.1.0.dist-info/WHEEL
filesystemlib-0.1.0.dist-info/top_level.txt
filesystemlib-0.1.0.dist-info/RECORD
