Metadata-Version: 2.1
Name: filesystemlib
Version: 0.1.0
Summary: Filesystem-related utilities
Home-page: https://github.com/chbrown/filesystemlib
Author: Christopher Brown
Author-email: io@henrian.com
License: MIT
Platform: UNKNOWN
Requires-Python: >=3.6
